py_common_utility/__init__.py
py_common_utility/obj/__init__.py
py_common_utility/obj/cache_provider.py
py_common_utility/obj/comm_logger.py
py_common_utility/utils/__init__.py
py_common_utility/utils/comm_utils.py
py_common_utility/utils/env_utils.py
py_common_utility/utils/file_utils.py
py_common_utility/utils/hash_utils.py
py_common_utility/utils/list_utils.py
py_common_utility/utils/reflection_util.py
py_common_utility/utils/time_utils.py
py_common_utility-0.1.5.dist-info/METADATA
py_common_utility-0.1.5.dist-info/WHEEL
py_common_utility-0.1.5.dist-info/RECORD
