Metadata-Version: 2.1
Name: py-common-utility
Version: 0.1.5
Summary: 
Author: kirin
Author-email: kirin.chen1001@gmail.com
Requires-Python: >=3.11,<4.0
Classifier: Programming Language :: Python :: 3
Classifier: Programming Language :: Python :: 3.11
Classifier: Programming Language :: Python :: 3.12
Requires-Dist: pathspec (>=0.12.1,<0.13.0)
Requires-Dist: python-dotenv (>=1.0.1,<2.0.0)
